disco/__init__.py
disco/main.py
disco/static/icon.svg
disco/static/index.html
disco/static/assets/allPaths-CzRwrDmy.js
disco/static/assets/allPathsLoader-EnLeFMZP.js
disco/static/assets/blueprint-icons-16-BC7K-1ZL.svg
disco/static/assets/blueprint-icons-16-C9UbJccz.eot
disco/static/assets/blueprint-icons-16-CbGmchD-.woff2
disco/static/assets/blueprint-icons-16-D1c4th_0.ttf
disco/static/assets/blueprint-icons-16-fZACaXWC.woff
disco/static/assets/blueprint-icons-20-B7C7CG8d.eot
disco/static/assets/blueprint-icons-20-BIpIp1In.ttf
disco/static/assets/blueprint-icons-20-C_UL887l.woff2
disco/static/assets/blueprint-icons-20-DCwisdmz.svg
disco/static/assets/blueprint-icons-20-DGO1e6fd.woff
disco/static/assets/index-BmDjQHI0.js
disco/static/assets/index-C3ZQnJ4p.css
disco/static/assets/index-DJwokFTj.js
disco/static/assets/index-DY_PFL8m.js
disco/static/assets/splitPathsBySizeLoader-DYuarY0V.js
disco_astronomy-1.0.0.dist-info/METADATA
disco_astronomy-1.0.0.dist-info/WHEEL
disco_astronomy-1.0.0.dist-info/entry_points.txt
disco_astronomy-1.0.0.dist-info/top_level.txt
disco_astronomy-1.0.0.dist-info/RECORD
