Metadata-Version: 2.4
Name: disco-astronomy
Version: 1.0.0
Summary: Herramienta de análisis de discos protoplanetarios
Author-email: astrojorgeluis <jorge.guzman.l@usach.cl>
Classifier: Programming Language :: Python :: 3
Classifier: License :: OSI Approved :: MIT License
Classifier: Operating System :: OS Independent
Requires-Python: >=3.9
Requires-Dist: fastapi
Requires-Dist: uvicorn[standard]
Requires-Dist: python-multipart
Requires-Dist: numpy
Requires-Dist: astropy
Requires-Dist: scipy
Requires-Dist: matplotlib
Requires-Dist: astroquery
